openswmm/CMakeLists.txt
openswmm/__init__.py
openswmm/_openswmm.pyx
openswmm/openswmm.pxd
openswmm/data/__init__.py
openswmm/gym/__init__.py
openswmm/output/CMakeLists.txt
openswmm/output/__init__.pxd
openswmm/output/__init__.py
openswmm/output/_output.pyi
openswmm/output/_output.pyx
openswmm/output/output.pxd
openswmm/solver/CMakeLists.txt
openswmm/solver/__init__.pxd
openswmm/solver/__init__.py
openswmm/solver/_solver.pyi
openswmm/solver/_solver.pyx
openswmm/solver/solver.pxd
openswmm-5.3.0.dev1.dist-info/licenses/LICENSE
tests/.DS_Store
tests/__init__.py
tests/test_swmm_solver.py
tests/test_swwm_output.py
tests/data/.DS_Store
tests/data/__init__.py
tests/data/output/__init__.py
tests/data/output/example_output_1.out
tests/data/output/json_time_series.pickle
tests/data/solver/__init__.py
tests/data/solver/non_existent_input_file.rpt
tests/data/solver/site_drainage_example.inp
tests/data/solver/site_drainage_example.rpt
openswmm-5.3.0.dev1.dist-info/METADATA
openswmm-5.3.0.dev1.dist-info/WHEEL
openswmm-5.3.0.dev1.dist-info/top_level.txt
openswmm-5.3.0.dev1.dist-info/RECORD
