Metadata-Version: 2.4
Name: openswmm
Version: 5.3.0.dev1
Summary: A python package for EPA SWMM preprocessing, solver, and post-processing.
Author-email: Caleb Buahin <caleb.buahin@gmail.com>
Maintainer-email: Caleb Buahin <caleb.buahin@gmail.com>
License: Copyright 2026 HydroCouple
Project-URL: Homepage, https://github.com/HydroCouple/Stormwater-Management-Model
Project-URL: Documentation, https://github.com/HydroCouple/Stormwater-Management-Model
Project-URL: Source Code, https://github.com/HydroCouple/Stormwater-Management-Model
Project-URL: Bug Tracker, https://github.com/HydroCouple/Stormwater-Management-Model/issues
Project-URL: Repository, https://github.com/HydroCouple/Stormwater-Management-Model
Project-URL: Changelog, https://github.com/HydroCouple/Stormwater-Management-Model/blob/master/CHANGELOG.md
Keywords: SWMM,storm water,modeling,water,hydrology,hydraulics,wastewater,machine learning,AI,GIS,environmental engineering,civil engineering
Classifier: Development Status :: 3 - Alpha
Classifier: Intended Audience :: Developers
Classifier: Intended Audience :: Science/Research
Classifier: Operating System :: OS Independent
Classifier: Programming Language :: Python :: 3.8
Classifier: Programming Language :: Python :: 3.9
Classifier: Programming Language :: Python :: 3.10
Classifier: Programming Language :: Python :: 3.11
Classifier: Programming Language :: Python :: 3.12
Classifier: Programming Language :: Python :: 3.13
Classifier: Programming Language :: C
Classifier: Programming Language :: C++
Classifier: Topic :: Scientific/Engineering
Classifier: Topic :: Scientific/Engineering :: Hydrology
Classifier: Topic :: Scientific/Engineering :: Mathematics
Classifier: Topic :: Scientific/Engineering :: Physics
Classifier: Topic :: Software Development :: Libraries
Classifier: Topic :: Scientific/Engineering :: Artificial Intelligence
Classifier: Topic :: Software Development :: Libraries :: Python Modules
Classifier: Topic :: Scientific/Engineering :: GIS
Requires-Python: >=3.8
License-File: LICENSE
Dynamic: description
Dynamic: description-content-type
Dynamic: license-file
